EasyDA/__init__.py
EasyDA/autofix.py
EasyDA/missing.py
EasyDA/preprocessing.py
EasyDA/summary.py
EasyDA/utilities.py
EasyDA/validation.py
EasyDA/visuals.py
easyda-0.0.1.dist-info/licenses/LICENSE
easyda-0.0.1.dist-info/METADATA
easyda-0.0.1.dist-info/WHEEL
easyda-0.0.1.dist-info/top_level.txt
easyda-0.0.1.dist-info/RECORD
